README.txt
setup.py
nginx/__init__.py
nginx/hello.py
pynginx.egg-info/PKG-INFO
pynginx.egg-info/SOURCES.txt
pynginx.egg-info/dependency_links.txt
pynginx.egg-info/top_level.txt