Metadata-Version: 1.0
Name: pynginx
Version: 0.0.0
Summary: control your nginx with python
Home-page: http://pypi.python.org/pypi/py_nginx
Author: Alex Zhang
Author-email: zchao1995@gmail.com
License: Apache 2.0
Platform: UNKNOWN
